{
  "main": {
    "id": "e70044b9eea79c12",
    "type": "split",
    "children": [
      {
        "id": "8760da83f5d37f06",
        "type": "tabs",
        "children": [
          {
            "id": "f4d9ad526c4d8f83",
            "type": "leaf",
            "state": {
              "type": "markdown",
              "state": {
                "file": "src/pages/blog/notes/2023-10-14 Xiao Seeed Exploration.md",
                "mode": "source",
                "source": false
              }
            }
          }
        ]
      }
    ],
    "direction": "vertical"
  },
  "left": {
    "id": "1d9918a07b43e787",
    "type": "split",
    "children": [
      {
        "id": "23b8e345cfd5d0fe",
        "type": "tabs",
        "children": [
          {
            "id": "6b9710d6c6cde1a9",
            "type": "leaf",
            "state": {
              "type": "file-explorer",
              "state": {
                "sortOrder": "alphabetical"
              }
            }
          },
          {
            "id": "96cdcc94d73733c4",
            "type": "leaf",
            "state": {
              "type": "search",
              "state": {
                "query": "",
                "matchingCase": false,
                "explainSearch": false,
                "collapseAll": false,
                "extraContext": false,
                "sortOrder": "alphabetical"
              }
            }
          },
          {
            "id": "583553ebd93ba30e",
            "type": "leaf",
            "state": {
              "type": "starred",
              "state": {}
            }
          },
          {
            "id": "10c443fb28f2600f",
            "type": "leaf",
            "state": {
              "type": "bookmarks",
              "state": {}
            }
          }
        ]
      }
    ],
    "direction": "horizontal",
    "width": 442.5
  },
  "right": {
    "id": "2a6a804d984df4cc",
    "type": "split",
    "children": [
      {
        "id": "8fafb9567db82daa",
        "type": "tabs",
        "children": [
          {
            "id": "37d70541176567f3",
            "type": "leaf",
            "state": {
              "type": "backlink",
              "state": {
                "file": "src/pages/blog/notes/2023-10-14 Xiao Seeed Exploration.md",
                "collapseAll": false,
                "extraContext": false,
                "sortOrder": "alphabetical",
                "showSearch": false,
                "searchQuery": "",
                "backlinkCollapsed": false,
                "unlinkedCollapsed": true
              }
            }
          },
          {
            "id": "92ebf0ab5d9ae4e6",
            "type": "leaf",
            "state": {
              "type": "outgoing-link",
              "state": {
                "file": "src/pages/blog/notes/2023-10-14 Xiao Seeed Exploration.md",
                "linksCollapsed": false,
                "unlinkedCollapsed": true
              }
            }
          },
          {
            "id": "da200dd2ea52f81c",
            "type": "leaf",
            "state": {
              "type": "tag",
              "state": {
                "sortOrder": "frequency",
                "useHierarchy": true
              }
            }
          },
          {
            "id": "6a4e650bc38ad020",
            "type": "leaf",
            "state": {
              "type": "outline",
              "state": {
                "file": "src/pages/blog/notes/2023-10-14 Xiao Seeed Exploration.md"
              }
            }
          },
          {
            "id": "459ece067fe671d8",
            "type": "leaf",
            "state": {
              "type": "all-properties",
              "state": {
                "sortOrder": "frequency"
              }
            }
          }
        ]
      }
    ],
    "direction": "horizontal",
    "width": 300,
    "collapsed": true
  },
  "left-ribbon": {
    "hiddenItems": {
      "switcher:Open quick switcher": false,
      "graph:Open graph view": false,
      "canvas:Create new canvas": false,
      "daily-notes:Open today's daily note": false,
      "templates:Insert template": false,
      "command-palette:Open command palette": false
    }
  },
  "active": "f4d9ad526c4d8f83",
  "lastOpenFiles": [
    "dist/_astro/cover@3762w.fe81a971.jpeg",
    "dist/_astro/cover@3371w.9093b11b.jpeg",
    "dist/_astro/cover@3058w.cd177337.jpeg",
    "dist/_astro/cover@3840w.10be2d0b.jpeg",
    "dist/_astro/cover@3605w.1016bc69.jpeg",
    "dist/_astro/cover@1024w.8177339e.jpeg",
    "dist/_astro/cover@2667w.4de2d175.jpeg",
    "dist/_astro/cover@2197w.729bf36b.jpeg",
    "dist/_astro/cover@1650w.bb0f01e8.jpeg",
    "dist/_astro/cover@320w.49716274.jpeg",
    "dist/cv/index.html",
    "dist/cv",
    "dist/old/index.html",
    "dist/old",
    "dist/blog/notes/2023-10-14 Xiao Seeed Exploration/index.html",
    "dist/blog/notes/2023-10-06 LaTeX/index.html",
    "dist/blog/notes/2023-09-4 Redoing this Blog/index.html",
    "dist/blog/notes/2023-04-06 Building a Basic NodeJS Server for NixOS/index.html",
    "dist/blog/notes/2023-02-05 Integrating with Obsidian/index.html",
    "dist/blog/notes/2023-02-05 Fusion Hooks/index.html",
    "dist/_astro/flag.689984e1.svg",
    "node_modules/@astrojs/markdown-component/readme.md",
    "node_modules/@astrojs/rss/README.md",
    "node_modules/strnum/README.md",
    "node_modules/fast-xml-parser/README.md",
    "node_modules/fast-xml-parser/CHANGELOG.md",
    "src/pages/blog/notes/2023-10-16 Transcript Splitting.md",
    "src/pages/blog/notes/2023-10-14 Xiao Seeed Exploration.md",
    "src/pages/blog/notes/2023-10-06 LaTeX.md",
    "resume/applications/sony-2023-10-09/application-playstation.md",
    "resume/applications/notion_so-2023-10-09/application-wiki.md",
    "resume/applications/notion_so-2023-10-09/application-software.md",
    "resume/applications/microsoft-2023-10-09/application-data.md",
    "resume/applications/netflix-2023-10-09/application.md",
    "resume/applications/discord-2023-10-09/application-video_audio.md",
    "resume/applications/crux_climate-2023-10-09/application-fullstack.md",
    "resume/applications/project_lead_the_way-2023-10-09/application-backend.md",
    "resume/applications/vityl-2023-10-09/application.md",
    "resume/applications/kittycad-2023-10-09/application-graphics.md",
    "resume/applications/fly_io-2023-10-09/application-infrastructure.md",
    "resume/applications/neurons_inc-2023-10-09/application.md",
    "resume/applications/seasony-2023-10-09/application-robotics.md",
    "resume/applications/seasony-2023-10-09/applixation-robotics.md",
    "resume/applications/holepunch-2023-10-09/application-general.md",
    "resume/applications/holepunch-2023-10-09/application-p2p-engineer.md",
    "resume/applications/holepunch-2023-10-09/application.md"
  ]
}